netgsm/__init__.py
netgsm/error_code.py
netgsm/exception.py
netgsm/service.py
NetGsm-0.0.7.dist-info/LICENSE
NetGsm-0.0.7.dist-info/METADATA
NetGsm-0.0.7.dist-info/WHEEL
NetGsm-0.0.7.dist-info/top_level.txt
NetGsm-0.0.7.dist-info/RECORD
